<?xml version="1.0" encoding="UTF-8" standalone="yes"?><w:document xmlns:mc="http://schemas.openxmlformats.org/markup-compatibility/2006" xmlns:o="urn:schemas-microsoft-com:office:office" xmlns:r="http://schemas.openxmlformats.org/officeDocument/2006/relationships" xmlns:m="http://schemas.openxmlformats.org/officeDocument/2006/math" xmlns:v="urn:schemas-microsoft-com:vml" xmlns:wp="http://schemas.openxmlformats.org/drawingml/2006/wordprocessingDrawing" xmlns:w10="urn:schemas-microsoft-com:office:word" xmlns:w="http://schemas.openxmlformats.org/wordprocessingml/2006/main" xmlns:wne="http://schemas.microsoft.com/office/word/2006/wordml" xmlns:sl="http://schemas.openxmlformats.org/schemaLibrary/2006/main" xmlns:a="http://schemas.openxmlformats.org/drawingml/2006/main" xmlns:pic="http://schemas.openxmlformats.org/drawingml/2006/picture" xmlns:c="http://schemas.openxmlformats.org/drawingml/2006/chart" xmlns:lc="http://schemas.openxmlformats.org/drawingml/2006/lockedCanvas" xmlns:dgm="http://schemas.openxmlformats.org/drawingml/2006/diagram" xmlns:wps="http://schemas.microsoft.com/office/word/2010/wordprocessingShape" xmlns:wpg="http://schemas.microsoft.com/office/word/2010/wordprocessingGroup" xmlns:w14="http://schemas.microsoft.com/office/word/2010/wordml" xmlns:w15="http://schemas.microsoft.com/office/word/2012/wordml" xmlns:w16="http://schemas.microsoft.com/office/word/2018/wordml" xmlns:w16cex="http://schemas.microsoft.com/office/word/2018/wordml/cex" xmlns:w16cid="http://schemas.microsoft.com/office/word/2016/wordml/cid" xmlns="http://schemas.microsoft.com/office/tasks/2019/documenttasks" xmlns:cr="http://schemas.microsoft.com/office/comments/2020/reactions"><w:background w:color="FFFFFF"/><w:body><w:p w:rsidR="00000000" w:rsidDel="00000000" w:rsidP="00000000" w:rsidRDefault="00000000" w:rsidRPr="00000000" w14:paraId="00000001"><w:pPr><w:rPr><w:rFonts w:ascii="Helvetica Neue" w:cs="Helvetica Neue" w:eastAsia="Helvetica Neue" w:hAnsi="Helvetica Neue"/><w:b w:val="1"/><w:bCs w:val="1"/></w:rPr></w:pPr><w:r w:rsidDel="00000000" w:rsidR="00000000" w:rsidRPr="00000000"><w:rPr><w:rtl w:val="0"/></w:rPr></w:r></w:p><w:p w:rsidR="00000000" w:rsidDel="00000000" w:rsidP="00000000" w:rsidRDefault="00000000" w:rsidRPr="00000000" w14:paraId="00000002"><w:pPr><w:rPr><w:b w:val="1"/><w:bCs w:val="1"/><w:color w:val="073763"/></w:rPr></w:pPr><w:r w:rsidDel="00000000" w:rsidR="00000000" w:rsidRPr="00000000"><w:rPr><w:rFonts w:ascii="Helvetica Neue" w:cs="Helvetica Neue" w:eastAsia="Helvetica Neue" w:hAnsi="Helvetica Neue"/><w:b w:val="1"/><w:bCs w:val="1"/><w:color w:val="073763"/><w:rtl w:val="0"/></w:rPr><w:t xml:space="preserve">Issued To :</w:t></w:r><w:r w:rsidDel="00000000" w:rsidR="00000000" w:rsidRPr="00000000"><w:rPr><w:rtl w:val="0"/></w:rPr></w:r></w:p><w:p w:rsidR="00000000" w:rsidDel="00000000" w:rsidP="00000000" w:rsidRDefault="00000000" w:rsidRPr="00000000" w14:paraId="00000003"><w:pPr><w:tabs><w:tab w:val="left" w:leader="none" w:pos="360"/></w:tabs><w:rPr><w:rFonts w:ascii="Helvetica Neue" w:cs="Helvetica Neue" w:eastAsia="Helvetica Neue" w:hAnsi="Helvetica Neue"/><w:b w:val="1"/><w:bCs w:val="1"/><w:color w:val="073763"/><w:sz w:val="30"/><w:szCs w:val="30"/></w:rPr></w:pPr><w:r w:rsidDel="00000000" w:rsidR="00000000" w:rsidRPr="00000000"><w:rPr><w:color w:val="073763"/><w:rtl w:val="0"/></w:rPr><w:tab/></w:r><w:r w:rsidDel="00000000" w:rsidR="00000000" w:rsidRPr="00000000"><w:rPr><w:rFonts w:ascii="Helvetica Neue" w:cs="Helvetica Neue" w:eastAsia="Helvetica Neue" w:hAnsi="Helvetica Neue"/><w:b w:val="1"/><w:bCs w:val="1"/><w:color w:val="073763"/><w:sz w:val="30"/><w:szCs w:val="30"/><w:rtl w:val="0"/></w:rPr><w:t xml:space="preserve">[Name] - [No_HP]</w:t></w:r></w:p><w:p w:rsidR="00000000" w:rsidDel="00000000" w:rsidP="00000000" w:rsidRDefault="00000000" w:rsidRPr="00000000" w14:paraId="00000004"><w:pPr><w:tabs><w:tab w:val="left" w:leader="none" w:pos="360"/></w:tabs><w:rPr><w:rFonts w:ascii="Helvetica Neue" w:cs="Helvetica Neue" w:eastAsia="Helvetica Neue" w:hAnsi="Helvetica Neue"/><w:color w:val="073763"/></w:rPr></w:pPr><w:r w:rsidDel="00000000" w:rsidR="00000000" w:rsidRPr="00000000"><w:rPr><w:rFonts w:ascii="Helvetica Neue" w:cs="Helvetica Neue" w:eastAsia="Helvetica Neue" w:hAnsi="Helvetica Neue"/><w:b w:val="1"/><w:bCs w:val="1"/><w:color w:val="073763"/><w:rtl w:val="0"/></w:rPr><w:tab/></w:r><w:r w:rsidDel="00000000" w:rsidR="00000000" w:rsidRPr="00000000"><w:rPr><w:rFonts w:ascii="Helvetica Neue" w:cs="Helvetica Neue" w:eastAsia="Helvetica Neue" w:hAnsi="Helvetica Neue"/><w:color w:val="073763"/><w:rtl w:val="0"/></w:rPr><w:t xml:space="preserve">[Bengkel]</w:t></w:r></w:p><w:p w:rsidR="00000000" w:rsidDel="00000000" w:rsidP="00000000" w:rsidRDefault="00000000" w:rsidRPr="00000000" w14:paraId="00000005"><w:pPr><w:tabs><w:tab w:val="left" w:leader="none" w:pos="360"/></w:tabs><w:rPr><w:rFonts w:ascii="Helvetica Neue" w:cs="Helvetica Neue" w:eastAsia="Helvetica Neue" w:hAnsi="Helvetica Neue"/><w:color w:val="073763"/></w:rPr></w:pPr><w:r w:rsidDel="00000000" w:rsidR="00000000" w:rsidRPr="00000000"><w:rPr><w:rtl w:val="0"/></w:rPr></w:r></w:p><w:tbl><w:tblPr><w:tblStyle w:val="Table1"/><w:tblW w:w="10425.0" w:type="dxa"/><w:jc w:val="left"/><w:tblBorders><w:top w:color="000000" w:space="0" w:sz="8" w:val="single"/><w:left w:color="000000" w:space="0" w:sz="8" w:val="single"/><w:bottom w:color="000000" w:space="0" w:sz="8" w:val="single"/><w:right w:color="000000" w:space="0" w:sz="8" w:val="single"/><w:insideH w:color="000000" w:space="0" w:sz="8" w:val="single"/><w:insideV w:color="000000" w:space="0" w:sz="8" w:val="single"/></w:tblBorders><w:tblLayout w:type="fixed"/><w:tblLook w:val="0600"/></w:tblPr><w:tblGrid><w:gridCol w:w="555"/><w:gridCol w:w="4950"/><w:gridCol w:w="1815"/><w:gridCol w:w="705"/><w:gridCol w:w="2400"/><w:tblGridChange w:id="0"><w:tblGrid><w:gridCol w:w="555"/><w:gridCol w:w="4950"/><w:gridCol w:w="1815"/><w:gridCol w:w="705"/><w:gridCol w:w="2400"/></w:tblGrid></w:tblGridChange></w:tblGrid><w:tr><w:trPr><w:cantSplit w:val="0"/><w:tblHeader w:val="0"/></w:trPr><w:tc><w:tcPr><w:tcBorders><w:top w:color="000000" w:space="0" w:sz="0" w:val="nil"/><w:left w:color="000000" w:space="0" w:sz="0" w:val="nil"/><w:bottom w:color="000000" w:space="0" w:sz="0" w:val="nil"/><w:right w:color="000000" w:space="0" w:sz="0" w:val="nil"/></w:tcBorders><w:shd w:fill="0b5394" w:val="clear"/><w:tcMar><w:top w:w="100.0" w:type="dxa"/><w:left w:w="100.0" w:type="dxa"/><w:bottom w:w="100.0" w:type="dxa"/><w:right w:w="100.0" w:type="dxa"/></w:tcMar><w:vAlign w:val="center"/></w:tcPr><w:p w:rsidR="00000000" w:rsidDel="00000000" w:rsidP="00000000" w:rsidRDefault="00000000" w:rsidRPr="00000000" w14:paraId="00000006"><w:pPr><w:keepNext w:val="0"/><w:keepLines w:val="0"/><w:widowControl w:val="0"/><w:pBdr><w:top w:space="0" w:sz="0" w:val="nil"/><w:left w:space="0" w:sz="0" w:val="nil"/><w:bottom w:space="0" w:sz="0" w:val="nil"/><w:right w:space="0" w:sz="0" w:val="nil"/><w:between w:space="0" w:sz="0" w:val="nil"/></w:pBdr><w:shd w:fill="auto" w:val="clear"/><w:spacing w:after="0" w:before="0" w:line="240" w:lineRule="auto"/><w:ind w:left="0" w:right="0" w:firstLine="0"/><w:jc w:val="center"/><w:rPr><w:rFonts w:ascii="Helvetica Neue" w:cs="Helvetica Neue" w:eastAsia="Helvetica Neue" w:hAnsi="Helvetica Neue"/><w:color w:val="ffffff"/></w:rPr></w:pPr><w:r w:rsidDel="00000000" w:rsidR="00000000" w:rsidRPr="00000000"><w:rPr><w:rFonts w:ascii="Helvetica Neue" w:cs="Helvetica Neue" w:eastAsia="Helvetica Neue" w:hAnsi="Helvetica Neue"/><w:color w:val="ffffff"/><w:rtl w:val="0"/></w:rPr><w:t xml:space="preserve">No</w:t></w:r></w:p></w:tc><w:tc><w:tcPr><w:tcBorders><w:top w:color="000000" w:space="0" w:sz="0" w:val="nil"/><w:left w:color="000000" w:space="0" w:sz="0" w:val="nil"/><w:bottom w:color="000000" w:space="0" w:sz="0" w:val="nil"/><w:right w:color="000000" w:space="0" w:sz="0" w:val="nil"/></w:tcBorders><w:shd w:fill="0b5394" w:val="clear"/><w:tcMar><w:top w:w="100.0" w:type="dxa"/><w:left w:w="100.0" w:type="dxa"/><w:bottom w:w="100.0" w:type="dxa"/><w:right w:w="100.0" w:type="dxa"/></w:tcMar><w:vAlign w:val="center"/></w:tcPr><w:p w:rsidR="00000000" w:rsidDel="00000000" w:rsidP="00000000" w:rsidRDefault="00000000" w:rsidRPr="00000000" w14:paraId="00000007"><w:pPr><w:keepNext w:val="0"/><w:keepLines w:val="0"/><w:widowControl w:val="0"/><w:pBdr><w:top w:space="0" w:sz="0" w:val="nil"/><w:left w:space="0" w:sz="0" w:val="nil"/><w:bottom w:space="0" w:sz="0" w:val="nil"/><w:right w:space="0" w:sz="0" w:val="nil"/><w:between w:space="0" w:sz="0" w:val="nil"/></w:pBdr><w:shd w:fill="auto" w:val="clear"/><w:spacing w:after="0" w:before="0" w:line="240" w:lineRule="auto"/><w:ind w:left="0" w:right="0" w:firstLine="0"/><w:jc w:val="center"/><w:rPr><w:rFonts w:ascii="Helvetica Neue" w:cs="Helvetica Neue" w:eastAsia="Helvetica Neue" w:hAnsi="Helvetica Neue"/><w:color w:val="ffffff"/></w:rPr></w:pPr><w:r w:rsidDel="00000000" w:rsidR="00000000" w:rsidRPr="00000000"><w:rPr><w:rFonts w:ascii="Helvetica Neue" w:cs="Helvetica Neue" w:eastAsia="Helvetica Neue" w:hAnsi="Helvetica Neue"/><w:color w:val="ffffff"/><w:rtl w:val="0"/></w:rPr><w:t xml:space="preserve">Item</w:t></w:r></w:p></w:tc><w:tc><w:tcPr><w:tcBorders><w:top w:color="000000" w:space="0" w:sz="0" w:val="nil"/><w:left w:color="000000" w:space="0" w:sz="0" w:val="nil"/><w:bottom w:color="000000" w:space="0" w:sz="0" w:val="nil"/><w:right w:color="000000" w:space="0" w:sz="0" w:val="nil"/></w:tcBorders><w:shd w:fill="0b5394" w:val="clear"/><w:tcMar><w:top w:w="100.0" w:type="dxa"/><w:left w:w="100.0" w:type="dxa"/><w:bottom w:w="100.0" w:type="dxa"/><w:right w:w="100.0" w:type="dxa"/></w:tcMar><w:vAlign w:val="center"/></w:tcPr><w:p w:rsidR="00000000" w:rsidDel="00000000" w:rsidP="00000000" w:rsidRDefault="00000000" w:rsidRPr="00000000" w14:paraId="00000008"><w:pPr><w:keepNext w:val="0"/><w:keepLines w:val="0"/><w:widowControl w:val="0"/><w:pBdr><w:top w:space="0" w:sz="0" w:val="nil"/><w:left w:space="0" w:sz="0" w:val="nil"/><w:bottom w:space="0" w:sz="0" w:val="nil"/><w:right w:space="0" w:sz="0" w:val="nil"/><w:between w:space="0" w:sz="0" w:val="nil"/></w:pBdr><w:shd w:fill="auto" w:val="clear"/><w:spacing w:after="0" w:before="0" w:line="240" w:lineRule="auto"/><w:ind w:left="0" w:right="0" w:firstLine="0"/><w:jc w:val="center"/><w:rPr><w:rFonts w:ascii="Helvetica Neue" w:cs="Helvetica Neue" w:eastAsia="Helvetica Neue" w:hAnsi="Helvetica Neue"/><w:color w:val="ffffff"/></w:rPr></w:pPr><w:r w:rsidDel="00000000" w:rsidR="00000000" w:rsidRPr="00000000"><w:rPr><w:rFonts w:ascii="Helvetica Neue" w:cs="Helvetica Neue" w:eastAsia="Helvetica Neue" w:hAnsi="Helvetica Neue"/><w:color w:val="ffffff"/><w:rtl w:val="0"/></w:rPr><w:t xml:space="preserve">Price</w:t></w:r></w:p></w:tc><w:tc><w:tcPr><w:tcBorders><w:top w:color="000000" w:space="0" w:sz="0" w:val="nil"/><w:left w:color="000000" w:space="0" w:sz="0" w:val="nil"/><w:bottom w:color="000000" w:space="0" w:sz="0" w:val="nil"/><w:right w:color="000000" w:space="0" w:sz="0" w:val="nil"/></w:tcBorders><w:shd w:fill="0b5394" w:val="clear"/><w:tcMar><w:top w:w="100.0" w:type="dxa"/><w:left w:w="100.0" w:type="dxa"/><w:bottom w:w="100.0" w:type="dxa"/><w:right w:w="100.0" w:type="dxa"/></w:tcMar><w:vAlign w:val="center"/></w:tcPr><w:p w:rsidR="00000000" w:rsidDel="00000000" w:rsidP="00000000" w:rsidRDefault="00000000" w:rsidRPr="00000000" w14:paraId="00000009"><w:pPr><w:keepNext w:val="0"/><w:keepLines w:val="0"/><w:widowControl w:val="0"/><w:pBdr><w:top w:space="0" w:sz="0" w:val="nil"/><w:left w:space="0" w:sz="0" w:val="nil"/><w:bottom w:space="0" w:sz="0" w:val="nil"/><w:right w:space="0" w:sz="0" w:val="nil"/><w:between w:space="0" w:sz="0" w:val="nil"/></w:pBdr><w:shd w:fill="auto" w:val="clear"/><w:spacing w:after="0" w:before="0" w:line="240" w:lineRule="auto"/><w:ind w:left="0" w:right="0" w:firstLine="0"/><w:jc w:val="center"/><w:rPr><w:rFonts w:ascii="Helvetica Neue" w:cs="Helvetica Neue" w:eastAsia="Helvetica Neue" w:hAnsi="Helvetica Neue"/><w:color w:val="ffffff"/></w:rPr></w:pPr><w:r w:rsidDel="00000000" w:rsidR="00000000" w:rsidRPr="00000000"><w:rPr><w:rFonts w:ascii="Helvetica Neue" w:cs="Helvetica Neue" w:eastAsia="Helvetica Neue" w:hAnsi="Helvetica Neue"/><w:color w:val="ffffff"/><w:rtl w:val="0"/></w:rPr><w:t xml:space="preserve">Qty</w:t></w:r></w:p></w:tc><w:tc><w:tcPr><w:tcBorders><w:top w:color="000000" w:space="0" w:sz="0" w:val="nil"/><w:left w:color="000000" w:space="0" w:sz="0" w:val="nil"/><w:bottom w:color="000000" w:space="0" w:sz="0" w:val="nil"/><w:right w:color="000000" w:space="0" w:sz="0" w:val="nil"/></w:tcBorders><w:shd w:fill="0b5394" w:val="clear"/><w:tcMar><w:top w:w="100.0" w:type="dxa"/><w:left w:w="100.0" w:type="dxa"/><w:bottom w:w="100.0" w:type="dxa"/><w:right w:w="100.0" w:type="dxa"/></w:tcMar><w:vAlign w:val="center"/></w:tcPr><w:p w:rsidR="00000000" w:rsidDel="00000000" w:rsidP="00000000" w:rsidRDefault="00000000" w:rsidRPr="00000000" w14:paraId="0000000A"><w:pPr><w:keepNext w:val="0"/><w:keepLines w:val="0"/><w:widowControl w:val="0"/><w:pBdr><w:top w:space="0" w:sz="0" w:val="nil"/><w:left w:space="0" w:sz="0" w:val="nil"/><w:bottom w:space="0" w:sz="0" w:val="nil"/><w:right w:space="0" w:sz="0" w:val="nil"/><w:between w:space="0" w:sz="0" w:val="nil"/></w:pBdr><w:shd w:fill="auto" w:val="clear"/><w:spacing w:after="0" w:before="0" w:line="240" w:lineRule="auto"/><w:ind w:left="0" w:right="0" w:firstLine="0"/><w:jc w:val="center"/><w:rPr><w:rFonts w:ascii="Helvetica Neue" w:cs="Helvetica Neue" w:eastAsia="Helvetica Neue" w:hAnsi="Helvetica Neue"/><w:color w:val="ffffff"/></w:rPr></w:pPr><w:r w:rsidDel="00000000" w:rsidR="00000000" w:rsidRPr="00000000"><w:rPr><w:rFonts w:ascii="Helvetica Neue" w:cs="Helvetica Neue" w:eastAsia="Helvetica Neue" w:hAnsi="Helvetica Neue"/><w:color w:val="ffffff"/><w:rtl w:val="0"/></w:rPr><w:t xml:space="preserve">Subtotal</w:t></w:r></w:p></w:tc></w:tr><w:tr><w:trPr><w:cantSplit w:val="0"/><w:tblHeader w:val="0"/></w:trPr><w:tc><w:tcPr><w:tcBorders><w:top w:color="000000" w:space="0" w:sz="0" w:val="nil"/><w:left w:color="000000" w:space="0" w:sz="0" w:val="nil"/><w:bottom w:color="000000" w:space="0" w:sz="0" w:val="nil"/><w:right w:color="000000" w:space="0" w:sz="0" w:val="nil"/></w:tcBorders><w:shd w:fill="auto" w:val="clear"/><w:tcMar><w:top w:w="100.0" w:type="dxa"/><w:left w:w="100.0" w:type="dxa"/><w:bottom w:w="100.0" w:type="dxa"/><w:right w:w="100.0" w:type="dxa"/></w:tcMar><w:vAlign w:val="center"/></w:tcPr><w:p w:rsidR="00000000" w:rsidDel="00000000" w:rsidP="00000000" w:rsidRDefault="00000000" w:rsidRPr="00000000" w14:paraId="0000000B"><w:pPr><w:keepNext w:val="0"/><w:keepLines w:val="0"/><w:widowControl w:val="0"/><w:pBdr><w:top w:space="0" w:sz="0" w:val="nil"/><w:left w:space="0" w:sz="0" w:val="nil"/><w:bottom w:space="0" w:sz="0" w:val="nil"/><w:right w:space="0" w:sz="0" w:val="nil"/><w:between w:space="0" w:sz="0" w:val="nil"/></w:pBdr><w:shd w:fill="auto" w:val="clear"/><w:spacing w:after="0" w:before="0" w:line="240" w:lineRule="auto"/><w:ind w:left="0" w:right="0" w:firstLine="0"/><w:jc w:val="center"/><w:rPr><w:rFonts w:ascii="Helvetica Neue" w:cs="Helvetica Neue" w:eastAsia="Helvetica Neue" w:hAnsi="Helvetica Neue"/><w:color w:val="073763"/></w:rPr></w:pPr><w:r w:rsidDel="00000000" w:rsidR="00000000" w:rsidRPr="00000000"><w:rPr><w:rFonts w:ascii="Helvetica Neue" w:cs="Helvetica Neue" w:eastAsia="Helvetica Neue" w:hAnsi="Helvetica Neue"/><w:color w:val="073763"/><w:rtl w:val="0"/></w:rPr><w:t xml:space="preserve">1</w:t></w:r></w:p></w:tc><w:tc><w:tcPr><w:tcBorders><w:top w:color="000000" w:space="0" w:sz="0" w:val="nil"/><w:left w:color="000000" w:space="0" w:sz="0" w:val="nil"/><w:bottom w:color="000000" w:space="0" w:sz="0" w:val="nil"/><w:right w:color="000000" w:space="0" w:sz="0" w:val="nil"/></w:tcBorders><w:shd w:fill="auto" w:val="clear"/><w:tcMar><w:top w:w="100.0" w:type="dxa"/><w:left w:w="100.0" w:type="dxa"/><w:bottom w:w="100.0" w:type="dxa"/><w:right w:w="100.0" w:type="dxa"/></w:tcMar><w:vAlign w:val="center"/></w:tcPr><w:p w:rsidR="00000000" w:rsidDel="00000000" w:rsidP="00000000" w:rsidRDefault="00000000" w:rsidRPr="00000000" w14:paraId="0000000C"><w:pPr><w:widowControl w:val="0"/><w:spacing w:line="240" w:lineRule="auto"/><w:rPr><w:rFonts w:ascii="Helvetica Neue" w:cs="Helvetica Neue" w:eastAsia="Helvetica Neue" w:hAnsi="Helvetica Neue"/><w:color w:val="073763"/></w:rPr></w:pPr><w:r w:rsidDel="00000000" w:rsidR="00000000" w:rsidRPr="00000000"><w:rPr><w:rFonts w:ascii="Helvetica Neue" w:cs="Helvetica Neue" w:eastAsia="Helvetica Neue" w:hAnsi="Helvetica Neue"/><w:color w:val="073763"/><w:rtl w:val="0"/></w:rPr><w:t xml:space="preserve">[Product] - [Qty] [Bundling]</w:t></w:r></w:p><w:p w:rsidR="00000000" w:rsidDel="00000000" w:rsidP="00000000" w:rsidRDefault="00000000" w:rsidRPr="00000000" w14:paraId="0000000D"><w:pPr><w:widowControl w:val="0"/><w:spacing w:line="240" w:lineRule="auto"/><w:rPr><w:rFonts w:ascii="Helvetica Neue" w:cs="Helvetica Neue" w:eastAsia="Helvetica Neue" w:hAnsi="Helvetica Neue"/><w:color w:val="073763"/></w:rPr></w:pPr><w:r w:rsidDel="00000000" w:rsidR="00000000" w:rsidRPr="00000000"><w:rPr><w:rFonts w:ascii="Helvetica Neue" w:cs="Helvetica Neue" w:eastAsia="Helvetica Neue" w:hAnsi="Helvetica Neue"/><w:color w:val="073763"/><w:rtl w:val="0"/></w:rPr><w:t xml:space="preserve">[Form_Detail]</w:t></w:r></w:p></w:tc><w:tc><w:tcPr><w:tcBorders><w:top w:color="000000" w:space="0" w:sz="0" w:val="nil"/><w:left w:color="000000" w:space="0" w:sz="0" w:val="nil"/><w:bottom w:color="000000" w:space="0" w:sz="0" w:val="nil"/><w:right w:color="000000" w:space="0" w:sz="0" w:val="nil"/></w:tcBorders><w:shd w:fill="auto" w:val="clear"/><w:tcMar><w:top w:w="100.0" w:type="dxa"/><w:left w:w="100.0" w:type="dxa"/><w:bottom w:w="100.0" w:type="dxa"/><w:right w:w="100.0" w:type="dxa"/></w:tcMar><w:vAlign w:val="center"/></w:tcPr><w:p w:rsidR="00000000" w:rsidDel="00000000" w:rsidP="00000000" w:rsidRDefault="00000000" w:rsidRPr="00000000" w14:paraId="0000000E"><w:pPr><w:widowControl w:val="0"/><w:spacing w:line="240" w:lineRule="auto"/><w:jc w:val="center"/><w:rPr><w:rFonts w:ascii="Helvetica Neue" w:cs="Helvetica Neue" w:eastAsia="Helvetica Neue" w:hAnsi="Helvetica Neue"/><w:color w:val="073763"/></w:rPr></w:pPr><w:r w:rsidDel="00000000" w:rsidR="00000000" w:rsidRPr="00000000"><w:rPr><w:rFonts w:ascii="Helvetica Neue" w:cs="Helvetica Neue" w:eastAsia="Helvetica Neue" w:hAnsi="Helvetica Neue"/><w:color w:val="073763"/><w:rtl w:val="0"/></w:rPr><w:t xml:space="preserve">[Price]</w:t></w:r></w:p></w:tc><w:tc><w:tcPr><w:tcBorders><w:top w:color="000000" w:space="0" w:sz="0" w:val="nil"/><w:left w:color="000000" w:space="0" w:sz="0" w:val="nil"/><w:bottom w:color="000000" w:space="0" w:sz="0" w:val="nil"/><w:right w:color="000000" w:space="0" w:sz="0" w:val="nil"/></w:tcBorders><w:shd w:fill="auto" w:val="clear"/><w:tcMar><w:top w:w="100.0" w:type="dxa"/><w:left w:w="100.0" w:type="dxa"/><w:bottom w:w="100.0" w:type="dxa"/><w:right w:w="100.0" w:type="dxa"/></w:tcMar><w:vAlign w:val="center"/></w:tcPr><w:p w:rsidR="00000000" w:rsidDel="00000000" w:rsidP="00000000" w:rsidRDefault="00000000" w:rsidRPr="00000000" w14:paraId="0000000F"><w:pPr><w:widowControl w:val="0"/><w:spacing w:line="240" w:lineRule="auto"/><w:jc w:val="center"/><w:rPr><w:rFonts w:ascii="Helvetica Neue" w:cs="Helvetica Neue" w:eastAsia="Helvetica Neue" w:hAnsi="Helvetica Neue"/><w:color w:val="073763"/></w:rPr></w:pPr><w:r w:rsidDel="00000000" w:rsidR="00000000" w:rsidRPr="00000000"><w:rPr><w:rFonts w:ascii="Helvetica Neue" w:cs="Helvetica Neue" w:eastAsia="Helvetica Neue" w:hAnsi="Helvetica Neue"/><w:color w:val="073763"/><w:rtl w:val="0"/></w:rPr><w:t xml:space="preserve">[Qty]</w:t></w:r></w:p></w:tc><w:tc><w:tcPr><w:tcBorders><w:top w:color="000000" w:space="0" w:sz="0" w:val="nil"/><w:left w:color="000000" w:space="0" w:sz="0" w:val="nil"/><w:bottom w:color="000000" w:space="0" w:sz="0" w:val="nil"/><w:right w:color="000000" w:space="0" w:sz="0" w:val="nil"/></w:tcBorders><w:shd w:fill="auto" w:val="clear"/><w:tcMar><w:top w:w="100.0" w:type="dxa"/><w:left w:w="100.0" w:type="dxa"/><w:bottom w:w="100.0" w:type="dxa"/><w:right w:w="100.0" w:type="dxa"/></w:tcMar><w:vAlign w:val="center"/></w:tcPr><w:p w:rsidR="00000000" w:rsidDel="00000000" w:rsidP="00000000" w:rsidRDefault="00000000" w:rsidRPr="00000000" w14:paraId="00000010"><w:pPr><w:widowControl w:val="0"/><w:spacing w:line="240" w:lineRule="auto"/><w:jc w:val="right"/><w:rPr><w:rFonts w:ascii="Helvetica Neue" w:cs="Helvetica Neue" w:eastAsia="Helvetica Neue" w:hAnsi="Helvetica Neue"/><w:color w:val="073763"/></w:rPr></w:pPr><w:r w:rsidDel="00000000" w:rsidR="00000000" w:rsidRPr="00000000"><w:rPr><w:rFonts w:ascii="Helvetica Neue" w:cs="Helvetica Neue" w:eastAsia="Helvetica Neue" w:hAnsi="Helvetica Neue"/><w:color w:val="073763"/><w:rtl w:val="0"/></w:rPr><w:t xml:space="preserve">[Subtotal]</w:t></w:r></w:p></w:tc></w:tr><w:tr><w:trPr><w:cantSplit w:val="0"/><w:tblHeader w:val="0"/></w:trPr><w:tc><w:tcPr><w:tcBorders><w:top w:color="000000" w:space="0" w:sz="0" w:val="nil"/><w:left w:color="000000" w:space="0" w:sz="0" w:val="nil"/><w:bottom w:color="000000" w:space="0" w:sz="0" w:val="nil"/><w:right w:color="000000" w:space="0" w:sz="0" w:val="nil"/></w:tcBorders><w:shd w:fill="auto" w:val="clear"/><w:tcMar><w:top w:w="100.0" w:type="dxa"/><w:left w:w="100.0" w:type="dxa"/><w:bottom w:w="100.0" w:type="dxa"/><w:right w:w="100.0" w:type="dxa"/></w:tcMar><w:vAlign w:val="center"/></w:tcPr><w:p w:rsidR="00000000" w:rsidDel="00000000" w:rsidP="00000000" w:rsidRDefault="00000000" w:rsidRPr="00000000" w14:paraId="00000011"><w:pPr><w:keepNext w:val="0"/><w:keepLines w:val="0"/><w:widowControl w:val="0"/><w:pBdr><w:top w:space="0" w:sz="0" w:val="nil"/><w:left w:space="0" w:sz="0" w:val="nil"/><w:bottom w:space="0" w:sz="0" w:val="nil"/><w:right w:space="0" w:sz="0" w:val="nil"/><w:between w:space="0" w:sz="0" w:val="nil"/></w:pBdr><w:shd w:fill="auto" w:val="clear"/><w:spacing w:after="0" w:before="0" w:line="240" w:lineRule="auto"/><w:ind w:left="0" w:right="0" w:firstLine="0"/><w:jc w:val="center"/><w:rPr><w:rFonts w:ascii="Helvetica Neue" w:cs="Helvetica Neue" w:eastAsia="Helvetica Neue" w:hAnsi="Helvetica Neue"/><w:color w:val="073763"/></w:rPr></w:pPr><w:r w:rsidDel="00000000" w:rsidR="00000000" w:rsidRPr="00000000"><w:rPr><w:rFonts w:ascii="Helvetica Neue" w:cs="Helvetica Neue" w:eastAsia="Helvetica Neue" w:hAnsi="Helvetica Neue"/><w:color w:val="073763"/><w:rtl w:val="0"/></w:rPr><w:t xml:space="preserve">2</w:t></w:r></w:p></w:tc><w:tc><w:tcPr><w:tcBorders><w:top w:color="000000" w:space="0" w:sz="0" w:val="nil"/><w:left w:color="000000" w:space="0" w:sz="0" w:val="nil"/><w:bottom w:color="000000" w:space="0" w:sz="0" w:val="nil"/><w:right w:color="000000" w:space="0" w:sz="0" w:val="nil"/></w:tcBorders><w:shd w:fill="auto" w:val="clear"/><w:tcMar><w:top w:w="100.0" w:type="dxa"/><w:left w:w="100.0" w:type="dxa"/><w:bottom w:w="100.0" w:type="dxa"/><w:right w:w="100.0" w:type="dxa"/></w:tcMar><w:vAlign w:val="center"/></w:tcPr><w:p w:rsidR="00000000" w:rsidDel="00000000" w:rsidP="00000000" w:rsidRDefault="00000000" w:rsidRPr="00000000" w14:paraId="00000012"><w:pPr><w:widowControl w:val="0"/><w:spacing w:line="240" w:lineRule="auto"/><w:rPr><w:rFonts w:ascii="Helvetica Neue" w:cs="Helvetica Neue" w:eastAsia="Helvetica Neue" w:hAnsi="Helvetica Neue"/><w:color w:val="073763"/></w:rPr></w:pPr><w:r w:rsidDel="00000000" w:rsidR="00000000" w:rsidRPr="00000000"><w:rPr><w:rFonts w:ascii="Helvetica Neue" w:cs="Helvetica Neue" w:eastAsia="Helvetica Neue" w:hAnsi="Helvetica Neue"/><w:color w:val="073763"/><w:rtl w:val="0"/></w:rPr><w:t xml:space="preserve">[Product] - [Qty] [Bundling]</w:t></w:r></w:p><w:p w:rsidR="00000000" w:rsidDel="00000000" w:rsidP="00000000" w:rsidRDefault="00000000" w:rsidRPr="00000000" w14:paraId="00000013"><w:pPr><w:widowControl w:val="0"/><w:spacing w:line="240" w:lineRule="auto"/><w:rPr><w:rFonts w:ascii="Helvetica Neue" w:cs="Helvetica Neue" w:eastAsia="Helvetica Neue" w:hAnsi="Helvetica Neue"/><w:color w:val="073763"/></w:rPr></w:pPr><w:r w:rsidDel="00000000" w:rsidR="00000000" w:rsidRPr="00000000"><w:rPr><w:rFonts w:ascii="Helvetica Neue" w:cs="Helvetica Neue" w:eastAsia="Helvetica Neue" w:hAnsi="Helvetica Neue"/><w:color w:val="073763"/><w:rtl w:val="0"/></w:rPr><w:t xml:space="preserve">[Form_Detail]</w:t></w:r></w:p></w:tc><w:tc><w:tcPr><w:tcBorders><w:top w:color="000000" w:space="0" w:sz="0" w:val="nil"/><w:left w:color="000000" w:space="0" w:sz="0" w:val="nil"/><w:bottom w:color="000000" w:space="0" w:sz="0" w:val="nil"/><w:right w:color="000000" w:space="0" w:sz="0" w:val="nil"/></w:tcBorders><w:shd w:fill="auto" w:val="clear"/><w:tcMar><w:top w:w="100.0" w:type="dxa"/><w:left w:w="100.0" w:type="dxa"/><w:bottom w:w="100.0" w:type="dxa"/><w:right w:w="100.0" w:type="dxa"/></w:tcMar><w:vAlign w:val="center"/></w:tcPr><w:p w:rsidR="00000000" w:rsidDel="00000000" w:rsidP="00000000" w:rsidRDefault="00000000" w:rsidRPr="00000000" w14:paraId="00000014"><w:pPr><w:widowControl w:val="0"/><w:spacing w:line="240" w:lineRule="auto"/><w:jc w:val="center"/><w:rPr><w:rFonts w:ascii="Helvetica Neue" w:cs="Helvetica Neue" w:eastAsia="Helvetica Neue" w:hAnsi="Helvetica Neue"/><w:color w:val="073763"/></w:rPr></w:pPr><w:r w:rsidDel="00000000" w:rsidR="00000000" w:rsidRPr="00000000"><w:rPr><w:rFonts w:ascii="Helvetica Neue" w:cs="Helvetica Neue" w:eastAsia="Helvetica Neue" w:hAnsi="Helvetica Neue"/><w:color w:val="073763"/><w:rtl w:val="0"/></w:rPr><w:t xml:space="preserve">[Price]</w:t></w:r></w:p></w:tc><w:tc><w:tcPr><w:tcBorders><w:top w:color="000000" w:space="0" w:sz="0" w:val="nil"/><w:left w:color="000000" w:space="0" w:sz="0" w:val="nil"/><w:bottom w:color="000000" w:space="0" w:sz="0" w:val="nil"/><w:right w:color="000000" w:space="0" w:sz="0" w:val="nil"/></w:tcBorders><w:shd w:fill="auto" w:val="clear"/><w:tcMar><w:top w:w="100.0" w:type="dxa"/><w:left w:w="100.0" w:type="dxa"/><w:bottom w:w="100.0" w:type="dxa"/><w:right w:w="100.0" w:type="dxa"/></w:tcMar><w:vAlign w:val="center"/></w:tcPr><w:p w:rsidR="00000000" w:rsidDel="00000000" w:rsidP="00000000" w:rsidRDefault="00000000" w:rsidRPr="00000000" w14:paraId="00000015"><w:pPr><w:widowControl w:val="0"/><w:spacing w:line="240" w:lineRule="auto"/><w:jc w:val="center"/><w:rPr><w:rFonts w:ascii="Helvetica Neue" w:cs="Helvetica Neue" w:eastAsia="Helvetica Neue" w:hAnsi="Helvetica Neue"/><w:color w:val="073763"/></w:rPr></w:pPr><w:r w:rsidDel="00000000" w:rsidR="00000000" w:rsidRPr="00000000"><w:rPr><w:rFonts w:ascii="Helvetica Neue" w:cs="Helvetica Neue" w:eastAsia="Helvetica Neue" w:hAnsi="Helvetica Neue"/><w:color w:val="073763"/><w:rtl w:val="0"/></w:rPr><w:t xml:space="preserve">[Qty]</w:t></w:r></w:p></w:tc><w:tc><w:tcPr><w:tcBorders><w:top w:color="000000" w:space="0" w:sz="0" w:val="nil"/><w:left w:color="000000" w:space="0" w:sz="0" w:val="nil"/><w:bottom w:color="000000" w:space="0" w:sz="0" w:val="nil"/><w:right w:color="000000" w:space="0" w:sz="0" w:val="nil"/></w:tcBorders><w:shd w:fill="auto" w:val="clear"/><w:tcMar><w:top w:w="100.0" w:type="dxa"/><w:left w:w="100.0" w:type="dxa"/><w:bottom w:w="100.0" w:type="dxa"/><w:right w:w="100.0" w:type="dxa"/></w:tcMar><w:vAlign w:val="center"/></w:tcPr><w:p w:rsidR="00000000" w:rsidDel="00000000" w:rsidP="00000000" w:rsidRDefault="00000000" w:rsidRPr="00000000" w14:paraId="00000016"><w:pPr><w:widowControl w:val="0"/><w:spacing w:line="240" w:lineRule="auto"/><w:jc w:val="right"/><w:rPr><w:rFonts w:ascii="Helvetica Neue" w:cs="Helvetica Neue" w:eastAsia="Helvetica Neue" w:hAnsi="Helvetica Neue"/><w:color w:val="073763"/></w:rPr></w:pPr><w:r w:rsidDel="00000000" w:rsidR="00000000" w:rsidRPr="00000000"><w:rPr><w:rFonts w:ascii="Helvetica Neue" w:cs="Helvetica Neue" w:eastAsia="Helvetica Neue" w:hAnsi="Helvetica Neue"/><w:color w:val="073763"/><w:rtl w:val="0"/></w:rPr><w:t xml:space="preserve">[Subtotal]</w:t></w:r></w:p></w:tc></w:tr><w:tr><w:trPr><w:cantSplit w:val="0"/><w:trHeight w:val="420" w:hRule="atLeast"/><w:tblHeader w:val="0"/></w:trPr><w:tc><w:tcPr><w:gridSpan w:val="4"/><w:tcBorders><w:top w:color="000000" w:space="0" w:sz="0" w:val="nil"/><w:left w:color="000000" w:space="0" w:sz="0" w:val="nil"/><w:bottom w:color="000000" w:space="0" w:sz="0" w:val="nil"/><w:right w:color="000000" w:space="0" w:sz="0" w:val="nil"/></w:tcBorders><w:shd w:fill="0b5394" w:val="clear"/><w:tcMar><w:top w:w="100.0" w:type="dxa"/><w:left w:w="100.0" w:type="dxa"/><w:bottom w:w="100.0" w:type="dxa"/><w:right w:w="100.0" w:type="dxa"/></w:tcMar><w:vAlign w:val="center"/></w:tcPr><w:p w:rsidR="00000000" w:rsidDel="00000000" w:rsidP="00000000" w:rsidRDefault="00000000" w:rsidRPr="00000000" w14:paraId="00000017"><w:pPr><w:keepNext w:val="0"/><w:keepLines w:val="0"/><w:widowControl w:val="0"/><w:pBdr><w:top w:space="0" w:sz="0" w:val="nil"/><w:left w:space="0" w:sz="0" w:val="nil"/><w:bottom w:space="0" w:sz="0" w:val="nil"/><w:right w:space="0" w:sz="0" w:val="nil"/><w:between w:space="0" w:sz="0" w:val="nil"/></w:pBdr><w:shd w:fill="auto" w:val="clear"/><w:spacing w:after="0" w:before="0" w:line="240" w:lineRule="auto"/><w:ind w:left="0" w:right="0" w:firstLine="0"/><w:jc w:val="right"/><w:rPr><w:rFonts w:ascii="Helvetica Neue" w:cs="Helvetica Neue" w:eastAsia="Helvetica Neue" w:hAnsi="Helvetica Neue"/><w:color w:val="ffffff"/></w:rPr></w:pPr><w:r w:rsidDel="00000000" w:rsidR="00000000" w:rsidRPr="00000000"><w:rPr><w:rFonts w:ascii="Helvetica Neue" w:cs="Helvetica Neue" w:eastAsia="Helvetica Neue" w:hAnsi="Helvetica Neue"/><w:color w:val="ffffff"/><w:rtl w:val="0"/></w:rPr><w:t xml:space="preserve">Shipping - [Shipping_Service]</w:t></w:r></w:p></w:tc><w:tc><w:tcPr><w:tcBorders><w:top w:color="000000" w:space="0" w:sz="0" w:val="nil"/><w:left w:color="000000" w:space="0" w:sz="0" w:val="nil"/><w:bottom w:color="000000" w:space="0" w:sz="0" w:val="nil"/><w:right w:color="000000" w:space="0" w:sz="0" w:val="nil"/></w:tcBorders><w:shd w:fill="0b5394" w:val="clear"/><w:tcMar><w:top w:w="100.0" w:type="dxa"/><w:left w:w="100.0" w:type="dxa"/><w:bottom w:w="100.0" w:type="dxa"/><w:right w:w="100.0" w:type="dxa"/></w:tcMar><w:vAlign w:val="center"/></w:tcPr><w:p w:rsidR="00000000" w:rsidDel="00000000" w:rsidP="00000000" w:rsidRDefault="00000000" w:rsidRPr="00000000" w14:paraId="0000001B"><w:pPr><w:keepNext w:val="0"/><w:keepLines w:val="0"/><w:widowControl w:val="0"/><w:pBdr><w:top w:space="0" w:sz="0" w:val="nil"/><w:left w:space="0" w:sz="0" w:val="nil"/><w:bottom w:space="0" w:sz="0" w:val="nil"/><w:right w:space="0" w:sz="0" w:val="nil"/><w:between w:space="0" w:sz="0" w:val="nil"/></w:pBdr><w:shd w:fill="auto" w:val="clear"/><w:spacing w:after="0" w:before="0" w:line="240" w:lineRule="auto"/><w:ind w:left="0" w:right="0" w:firstLine="0"/><w:jc w:val="right"/><w:rPr><w:rFonts w:ascii="Helvetica Neue" w:cs="Helvetica Neue" w:eastAsia="Helvetica Neue" w:hAnsi="Helvetica Neue"/><w:color w:val="ffffff"/></w:rPr></w:pPr><w:r w:rsidDel="00000000" w:rsidR="00000000" w:rsidRPr="00000000"><w:rPr><w:rFonts w:ascii="Helvetica Neue" w:cs="Helvetica Neue" w:eastAsia="Helvetica Neue" w:hAnsi="Helvetica Neue"/><w:color w:val="ffffff"/><w:rtl w:val="0"/></w:rPr><w:t xml:space="preserve">[Shipping_Total]</w:t></w:r></w:p></w:tc></w:tr><w:tr><w:trPr><w:cantSplit w:val="0"/><w:trHeight w:val="420" w:hRule="atLeast"/><w:tblHeader w:val="0"/></w:trPr><w:tc><w:tcPr><w:gridSpan w:val="4"/><w:tcBorders><w:top w:color="000000" w:space="0" w:sz="0" w:val="nil"/><w:left w:color="000000" w:space="0" w:sz="0" w:val="nil"/><w:bottom w:color="000000" w:space="0" w:sz="0" w:val="nil"/><w:right w:color="000000" w:space="0" w:sz="0" w:val="nil"/></w:tcBorders><w:shd w:fill="0b5394" w:val="clear"/><w:tcMar><w:top w:w="100.0" w:type="dxa"/><w:left w:w="100.0" w:type="dxa"/><w:bottom w:w="100.0" w:type="dxa"/><w:right w:w="100.0" w:type="dxa"/></w:tcMar><w:vAlign w:val="center"/></w:tcPr><w:p w:rsidR="00000000" w:rsidDel="00000000" w:rsidP="00000000" w:rsidRDefault="00000000" w:rsidRPr="00000000" w14:paraId="0000001C"><w:pPr><w:keepNext w:val="0"/><w:keepLines w:val="0"/><w:widowControl w:val="0"/><w:pBdr><w:top w:space="0" w:sz="0" w:val="nil"/><w:left w:space="0" w:sz="0" w:val="nil"/><w:bottom w:space="0" w:sz="0" w:val="nil"/><w:right w:space="0" w:sz="0" w:val="nil"/><w:between w:space="0" w:sz="0" w:val="nil"/></w:pBdr><w:shd w:fill="auto" w:val="clear"/><w:spacing w:after="0" w:before="0" w:line="240" w:lineRule="auto"/><w:ind w:left="0" w:right="0" w:firstLine="0"/><w:jc w:val="right"/><w:rPr><w:rFonts w:ascii="Helvetica Neue" w:cs="Helvetica Neue" w:eastAsia="Helvetica Neue" w:hAnsi="Helvetica Neue"/><w:color w:val="ffffff"/></w:rPr></w:pPr><w:r w:rsidDel="00000000" w:rsidR="00000000" w:rsidRPr="00000000"><w:rPr><w:rFonts w:ascii="Helvetica Neue" w:cs="Helvetica Neue" w:eastAsia="Helvetica Neue" w:hAnsi="Helvetica Neue"/><w:color w:val="ffffff"/><w:rtl w:val="0"/></w:rPr><w:t xml:space="preserve">Grand Total</w:t></w:r></w:p></w:tc><w:tc><w:tcPr><w:tcBorders><w:top w:color="000000" w:space="0" w:sz="0" w:val="nil"/><w:left w:color="000000" w:space="0" w:sz="0" w:val="nil"/><w:bottom w:color="000000" w:space="0" w:sz="0" w:val="nil"/><w:right w:color="000000" w:space="0" w:sz="0" w:val="nil"/></w:tcBorders><w:shd w:fill="0b5394" w:val="clear"/><w:tcMar><w:top w:w="100.0" w:type="dxa"/><w:left w:w="100.0" w:type="dxa"/><w:bottom w:w="100.0" w:type="dxa"/><w:right w:w="100.0" w:type="dxa"/></w:tcMar><w:vAlign w:val="center"/></w:tcPr><w:p w:rsidR="00000000" w:rsidDel="00000000" w:rsidP="00000000" w:rsidRDefault="00000000" w:rsidRPr="00000000" w14:paraId="00000020"><w:pPr><w:keepNext w:val="0"/><w:keepLines w:val="0"/><w:widowControl w:val="0"/><w:pBdr><w:top w:space="0" w:sz="0" w:val="nil"/><w:left w:space="0" w:sz="0" w:val="nil"/><w:bottom w:space="0" w:sz="0" w:val="nil"/><w:right w:space="0" w:sz="0" w:val="nil"/><w:between w:space="0" w:sz="0" w:val="nil"/></w:pBdr><w:shd w:fill="auto" w:val="clear"/><w:spacing w:after="0" w:before="0" w:line="240" w:lineRule="auto"/><w:ind w:left="0" w:right="0" w:firstLine="0"/><w:jc w:val="right"/><w:rPr><w:rFonts w:ascii="Helvetica Neue" w:cs="Helvetica Neue" w:eastAsia="Helvetica Neue" w:hAnsi="Helvetica Neue"/><w:color w:val="ffffff"/></w:rPr></w:pPr><w:r w:rsidDel="00000000" w:rsidR="00000000" w:rsidRPr="00000000"><w:rPr><w:rFonts w:ascii="Helvetica Neue" w:cs="Helvetica Neue" w:eastAsia="Helvetica Neue" w:hAnsi="Helvetica Neue"/><w:color w:val="ffffff"/><w:rtl w:val="0"/></w:rPr><w:t xml:space="preserve">[Grand_Total]</w:t></w:r></w:p></w:tc></w:tr></w:tbl><w:p w:rsidR="00000000" w:rsidDel="00000000" w:rsidP="00000000" w:rsidRDefault="00000000" w:rsidRPr="00000000" w14:paraId="00000021"><w:pPr><w:tabs><w:tab w:val="left" w:leader="none" w:pos="360"/></w:tabs><w:spacing w:line="240" w:lineRule="auto"/><w:rPr><w:rFonts w:ascii="Helvetica Neue" w:cs="Helvetica Neue" w:eastAsia="Helvetica Neue" w:hAnsi="Helvetica Neue"/><w:b w:val="1"/><w:bCs w:val="1"/><w:sz w:val="42"/><w:szCs w:val="42"/></w:rPr></w:pPr><w:r w:rsidDel="00000000" w:rsidR="00000000" w:rsidRPr="00000000"><w:rPr><w:rtl w:val="0"/></w:rPr></w:r></w:p><w:tbl><w:tblPr><w:tblStyle w:val="Table2"/><w:tblW w:w="10440.0" w:type="dxa"/><w:jc w:val="left"/><w:tblBorders><w:top w:color="000000" w:space="0" w:sz="8" w:val="single"/><w:left w:color="000000" w:space="0" w:sz="8" w:val="single"/><w:bottom w:color="000000" w:space="0" w:sz="8" w:val="single"/><w:right w:color="000000" w:space="0" w:sz="8" w:val="single"/><w:insideH w:color="000000" w:space="0" w:sz="8" w:val="single"/><w:insideV w:color="000000" w:space="0" w:sz="8" w:val="single"/></w:tblBorders><w:tblLayout w:type="fixed"/><w:tblLook w:val="0600"/></w:tblPr><w:tblGrid><w:gridCol w:w="7830"/><w:gridCol w:w="2610"/><w:tblGridChange w:id="0"><w:tblGrid><w:gridCol w:w="7830"/><w:gridCol w:w="2610"/></w:tblGrid></w:tblGridChange></w:tblGrid><w:tr><w:trPr><w:cantSplit w:val="0"/><w:trHeight w:val="144" w:hRule="atLeast"/><w:tblHeader w:val="0"/></w:trPr><w:tc><w:tcPr><w:tcBorders><w:top w:color="000000" w:space="0" w:sz="0" w:val="nil"/><w:left w:color="000000" w:space="0" w:sz="0" w:val="nil"/><w:bottom w:color="000000" w:space="0" w:sz="0" w:val="nil"/><w:right w:color="000000" w:space="0" w:sz="0" w:val="nil"/></w:tcBorders><w:shd w:fill="auto" w:val="clear"/><w:tcMar><w:top w:w="100.0" w:type="dxa"/><w:left w:w="100.0" w:type="dxa"/><w:bottom w:w="100.0" w:type="dxa"/><w:right w:w="100.0" w:type="dxa"/></w:tcMar><w:vAlign w:val="top"/></w:tcPr><w:p w:rsidR="00000000" w:rsidDel="00000000" w:rsidP="00000000" w:rsidRDefault="00000000" w:rsidRPr="00000000" w14:paraId="00000022"><w:pPr><w:tabs><w:tab w:val="left" w:leader="none" w:pos="360"/></w:tabs><w:spacing w:after="240" w:before="0" w:line="240" w:lineRule="auto"/><w:rPr><w:rFonts w:ascii="Helvetica Neue" w:cs="Helvetica Neue" w:eastAsia="Helvetica Neue" w:hAnsi="Helvetica Neue"/><w:b w:val="1"/><w:bCs w:val="1"/><w:color w:val="073763"/><w:sz w:val="42"/><w:szCs w:val="42"/></w:rPr></w:pPr><w:r w:rsidDel="00000000" w:rsidR="00000000" w:rsidRPr="00000000"><w:rPr><w:rFonts w:ascii="Helvetica Neue" w:cs="Helvetica Neue" w:eastAsia="Helvetica Neue" w:hAnsi="Helvetica Neue"/><w:b w:val="1"/><w:bCs w:val="1"/><w:color w:val="073763"/><w:sz w:val="42"/><w:szCs w:val="42"/><w:rtl w:val="0"/></w:rPr><w:t xml:space="preserve">Payment Info :</w:t></w:r></w:p></w:tc><w:tc><w:tcPr><w:vMerge w:val="restart"/><w:tcBorders><w:top w:color="000000" w:space="0" w:sz="0" w:val="nil"/><w:left w:color="000000" w:space="0" w:sz="0" w:val="nil"/><w:bottom w:color="000000" w:space="0" w:sz="0" w:val="nil"/><w:right w:color="000000" w:space="0" w:sz="0" w:val="nil"/></w:tcBorders><w:shd w:fill="auto" w:val="clear"/><w:tcMar><w:top w:w="100.0" w:type="dxa"/><w:left w:w="100.0" w:type="dxa"/><w:bottom w:w="100.0" w:type="dxa"/><w:right w:w="100.0" w:type="dxa"/></w:tcMar></w:tcPr><w:p w:rsidR="00000000" w:rsidDel="00000000" w:rsidP="00000000" w:rsidRDefault="00000000" w:rsidRPr="00000000" w14:paraId="00000023"><w:pPr><w:keepNext w:val="0"/><w:keepLines w:val="0"/><w:widowControl w:val="0"/><w:pBdr><w:top w:space="0" w:sz="0" w:val="nil"/><w:left w:space="0" w:sz="0" w:val="nil"/><w:bottom w:space="0" w:sz="0" w:val="nil"/><w:right w:space="0" w:sz="0" w:val="nil"/><w:between w:space="0" w:sz="0" w:val="nil"/></w:pBdr><w:shd w:fill="auto" w:val="clear"/><w:spacing w:after="0" w:before="0" w:line="240" w:lineRule="auto"/><w:ind w:left="0" w:right="0" w:firstLine="0"/><w:jc w:val="right"/><w:rPr><w:rFonts w:ascii="Helvetica Neue" w:cs="Helvetica Neue" w:eastAsia="Helvetica Neue" w:hAnsi="Helvetica Neue"/><w:b w:val="1"/><w:bCs w:val="1"/><w:color w:val="073763"/><w:sz w:val="42"/><w:szCs w:val="42"/></w:rPr></w:pPr><w:r w:rsidDel="00000000" w:rsidR="00000000" w:rsidRPr="00000000"><w:rPr><w:rFonts w:ascii="Helvetica Neue" w:cs="Helvetica Neue" w:eastAsia="Helvetica Neue" w:hAnsi="Helvetica Neue"/><w:b w:val="1"/><w:bCs w:val="1"/><w:color w:val="073763"/><w:sz w:val="42"/><w:szCs w:val="42"/></w:rPr><w:drawing><wp:inline distB="114300" distT="114300" distL="114300" distR="114300"><wp:extent cx="976313" cy="976313"/><wp:effectExtent b="0" l="0" r="0" t="0"/><wp:docPr id="2" name="image2.png"/><a:graphic><a:graphicData uri="http://schemas.openxmlformats.org/drawingml/2006/picture"><pic:pic><pic:nvPicPr><pic:cNvPr id="0" name="image2.png"/><pic:cNvPicPr preferRelativeResize="0"/></pic:nvPicPr><pic:blipFill><a:blip r:embed="rId6"/><a:srcRect b="0" l="0" r="0" t="0"/><a:stretch><a:fillRect/></a:stretch></pic:blipFill><pic:spPr><a:xfrm><a:off x="0" y="0"/><a:ext cx="976313" cy="976313"/></a:xfrm><a:prstGeom prst="rect"/><a:ln/></pic:spPr></pic:pic></a:graphicData></a:graphic></wp:inline></w:drawing></w:r><w:r w:rsidDel="00000000" w:rsidR="00000000" w:rsidRPr="00000000"><w:rPr><w:rtl w:val="0"/></w:rPr></w:r></w:p></w:tc></w:tr><w:tr><w:trPr><w:cantSplit w:val="0"/><w:trHeight w:val="576" w:hRule="atLeast"/><w:tblHeader w:val="0"/></w:trPr><w:tc><w:tcPr><w:tcBorders><w:top w:color="000000" w:space="0" w:sz="0" w:val="nil"/><w:left w:color="000000" w:space="0" w:sz="0" w:val="nil"/><w:bottom w:color="000000" w:space="0" w:sz="0" w:val="nil"/><w:right w:color="000000" w:space="0" w:sz="0" w:val="nil"/></w:tcBorders><w:shd w:fill="auto" w:val="clear"/><w:tcMar><w:top w:w="100.0" w:type="dxa"/><w:left w:w="100.0" w:type="dxa"/><w:bottom w:w="100.0" w:type="dxa"/><w:right w:w="100.0" w:type="dxa"/></w:tcMar><w:vAlign w:val="bottom"/></w:tcPr><w:p w:rsidR="00000000" w:rsidDel="00000000" w:rsidP="00000000" w:rsidRDefault="00000000" w:rsidRPr="00000000" w14:paraId="00000024"><w:pPr><w:tabs><w:tab w:val="left" w:leader="none" w:pos="360"/></w:tabs><w:spacing w:after="240" w:line="240" w:lineRule="auto"/><w:rPr><w:rFonts w:ascii="Helvetica Neue" w:cs="Helvetica Neue" w:eastAsia="Helvetica Neue" w:hAnsi="Helvetica Neue"/><w:b w:val="1"/><w:bCs w:val="1"/><w:color w:val="073763"/><w:sz w:val="42"/><w:szCs w:val="42"/></w:rPr></w:pPr><w:r w:rsidDel="00000000" w:rsidR="00000000" w:rsidRPr="00000000"><w:rPr><w:rFonts w:ascii="Helvetica Neue" w:cs="Helvetica Neue" w:eastAsia="Helvetica Neue" w:hAnsi="Helvetica Neue"/><w:b w:val="1"/><w:bCs w:val="1"/><w:color w:val="073763"/><w:sz w:val="42"/><w:szCs w:val="42"/><w:rtl w:val="0"/></w:rPr><w:t xml:space="preserve">BCA 7615417378 a.n. Matthew Utama</w:t></w:r></w:p></w:tc><w:tc><w:tcPr><w:vMerge w:val="continue"/><w:tcBorders><w:top w:color="000000" w:space="0" w:sz="0" w:val="nil"/><w:left w:color="000000" w:space="0" w:sz="0" w:val="nil"/><w:bottom w:color="000000" w:space="0" w:sz="0" w:val="nil"/><w:right w:color="000000" w:space="0" w:sz="0" w:val="nil"/></w:tcBorders><w:shd w:fill="auto" w:val="clear"/><w:tcMar><w:top w:w="100.0" w:type="dxa"/><w:left w:w="100.0" w:type="dxa"/><w:bottom w:w="100.0" w:type="dxa"/><w:right w:w="100.0" w:type="dxa"/></w:tcMar></w:tcPr><w:p w:rsidR="00000000" w:rsidDel="00000000" w:rsidP="00000000" w:rsidRDefault="00000000" w:rsidRPr="00000000" w14:paraId="00000025"><w:pPr><w:keepNext w:val="0"/><w:keepLines w:val="0"/><w:pageBreakBefore w:val="0"/><w:widowControl w:val="0"/><w:pBdr><w:top w:space="0" w:sz="0" w:val="nil"/><w:left w:space="0" w:sz="0" w:val="nil"/><w:bottom w:space="0" w:sz="0" w:val="nil"/><w:right w:space="0" w:sz="0" w:val="nil"/><w:between w:space="0" w:sz="0" w:val="nil"/></w:pBdr><w:shd w:fill="auto" w:val="clear"/><w:spacing w:after="0" w:before="0" w:line="276" w:lineRule="auto"/><w:ind w:left="0" w:right="0" w:firstLine="0"/><w:jc w:val="left"/><w:rPr><w:rFonts w:ascii="Helvetica Neue" w:cs="Helvetica Neue" w:eastAsia="Helvetica Neue" w:hAnsi="Helvetica Neue"/><w:b w:val="1"/><w:bCs w:val="1"/><w:sz w:val="42"/><w:szCs w:val="42"/></w:rPr></w:pPr><w:r w:rsidDel="00000000" w:rsidR="00000000" w:rsidRPr="00000000"><w:rPr><w:rtl w:val="0"/></w:rPr></w:r></w:p></w:tc></w:tr></w:tbl><w:p w:rsidR="00000000" w:rsidDel="00000000" w:rsidP="00000000" w:rsidRDefault="00000000" w:rsidRPr="00000000" w14:paraId="00000026"><w:pPr><w:tabs><w:tab w:val="left" w:leader="none" w:pos="360"/></w:tabs><w:spacing w:after="0" w:before="0" w:line="240" w:lineRule="auto"/><w:rPr><w:rFonts w:ascii="Helvetica Neue" w:cs="Helvetica Neue" w:eastAsia="Helvetica Neue" w:hAnsi="Helvetica Neue"/><w:color w:val="073763"/></w:rPr></w:pPr><w:r w:rsidDel="00000000" w:rsidR="00000000" w:rsidRPr="00000000"><w:rPr><w:rtl w:val="0"/></w:rPr></w:r></w:p><w:p w:rsidR="00000000" w:rsidDel="00000000" w:rsidP="00000000" w:rsidRDefault="00000000" w:rsidRPr="00000000" w14:paraId="00000027"><w:pPr><w:tabs><w:tab w:val="left" w:leader="none" w:pos="360"/></w:tabs><w:spacing w:after="0" w:before="0" w:line="240" w:lineRule="auto"/><w:rPr><w:rFonts w:ascii="Helvetica Neue" w:cs="Helvetica Neue" w:eastAsia="Helvetica Neue" w:hAnsi="Helvetica Neue"/><w:color w:val="073763"/></w:rPr></w:pPr><w:r w:rsidDel="00000000" w:rsidR="00000000" w:rsidRPr="00000000"><w:rPr><w:rFonts w:ascii="Helvetica Neue" w:cs="Helvetica Neue" w:eastAsia="Helvetica Neue" w:hAnsi="Helvetica Neue"/><w:b w:val="1"/><w:bCs w:val="1"/><w:color w:val="073763"/><w:sz w:val="42"/><w:szCs w:val="42"/><w:rtl w:val="0"/></w:rPr><w:t xml:space="preserve">Terms and Condition</w:t></w:r><w:r w:rsidDel="00000000" w:rsidR="00000000" w:rsidRPr="00000000"><w:rPr><w:rtl w:val="0"/></w:rPr></w:r></w:p><w:p w:rsidR="00000000" w:rsidDel="00000000" w:rsidP="00000000" w:rsidRDefault="00000000" w:rsidRPr="00000000" w14:paraId="00000028"><w:pPr><w:tabs><w:tab w:val="left" w:leader="none" w:pos="360"/></w:tabs><w:spacing w:after="0" w:before="0" w:line="240" w:lineRule="auto"/><w:rPr><w:rFonts w:ascii="Helvetica Neue" w:cs="Helvetica Neue" w:eastAsia="Helvetica Neue" w:hAnsi="Helvetica Neue"/><w:color w:val="073763"/></w:rPr></w:pPr><w:r w:rsidDel="00000000" w:rsidR="00000000" w:rsidRPr="00000000"><w:rPr><w:rFonts w:ascii="Helvetica Neue" w:cs="Helvetica Neue" w:eastAsia="Helvetica Neue" w:hAnsi="Helvetica Neue"/><w:color w:val="073763"/><w:rtl w:val="0"/></w:rPr><w:t xml:space="preserve">Preview design akan dikirim setelah payment. Proses editing berjalan ± 2 hari, dan produksi berjalan ± 4 hari kerja. Durasi diatas merupakan estimasi dan akan menyesuaikan dengan antrian pesanan.</w:t></w:r></w:p><w:p w:rsidR="00000000" w:rsidDel="00000000" w:rsidP="00000000" w:rsidRDefault="00000000" w:rsidRPr="00000000" w14:paraId="00000029"><w:pPr><w:tabs><w:tab w:val="left" w:leader="none" w:pos="360"/></w:tabs><w:spacing w:after="0" w:before="0" w:line="240" w:lineRule="auto"/><w:rPr><w:rFonts w:ascii="Helvetica Neue" w:cs="Helvetica Neue" w:eastAsia="Helvetica Neue" w:hAnsi="Helvetica Neue"/><w:color w:val="073763"/></w:rPr></w:pPr><w:r w:rsidDel="00000000" w:rsidR="00000000" w:rsidRPr="00000000"><w:rPr><w:rtl w:val="0"/></w:rPr></w:r></w:p><w:p w:rsidR="00000000" w:rsidDel="00000000" w:rsidP="00000000" w:rsidRDefault="00000000" w:rsidRPr="00000000" w14:paraId="0000002A"><w:pPr><w:tabs><w:tab w:val="left" w:leader="none" w:pos="360"/></w:tabs><w:spacing w:after="0" w:before="0" w:line="240" w:lineRule="auto"/><w:rPr><w:rFonts w:ascii="Helvetica Neue" w:cs="Helvetica Neue" w:eastAsia="Helvetica Neue" w:hAnsi="Helvetica Neue"/><w:color w:val="073763"/></w:rPr></w:pPr><w:r w:rsidDel="00000000" w:rsidR="00000000" w:rsidRPr="00000000"><w:rPr><w:rFonts w:ascii="Helvetica Neue" w:cs="Helvetica Neue" w:eastAsia="Helvetica Neue" w:hAnsi="Helvetica Neue"/><w:color w:val="073763"/><w:rtl w:val="0"/></w:rPr><w:t xml:space="preserve">Apabila ada kesalahan pada draft design dapat mengambil revisi sebanyak 1x.</w:t></w:r></w:p><w:p w:rsidR="00000000" w:rsidDel="00000000" w:rsidP="00000000" w:rsidRDefault="00000000" w:rsidRPr="00000000" w14:paraId="0000002B"><w:pPr><w:tabs><w:tab w:val="left" w:leader="none" w:pos="360"/></w:tabs><w:spacing w:after="0" w:before="0" w:line="240" w:lineRule="auto"/><w:rPr><w:rFonts w:ascii="Helvetica Neue" w:cs="Helvetica Neue" w:eastAsia="Helvetica Neue" w:hAnsi="Helvetica Neue"/><w:color w:val="073763"/></w:rPr></w:pPr><w:r w:rsidDel="00000000" w:rsidR="00000000" w:rsidRPr="00000000"><w:rPr><w:rFonts w:ascii="Helvetica Neue" w:cs="Helvetica Neue" w:eastAsia="Helvetica Neue" w:hAnsi="Helvetica Neue"/><w:color w:val="073763"/><w:rtl w:val="0"/></w:rPr><w:t xml:space="preserve">Harap untuk menjabarkan revisi yang mau dilakukan dengan detail dan jelas. Revisi berikutnya akan dikenakan biaya 25rb.</w:t></w:r></w:p><w:p w:rsidR="00000000" w:rsidDel="00000000" w:rsidP="00000000" w:rsidRDefault="00000000" w:rsidRPr="00000000" w14:paraId="0000002C"><w:pPr><w:tabs><w:tab w:val="left" w:leader="none" w:pos="360"/></w:tabs><w:spacing w:after="0" w:before="0" w:line="240" w:lineRule="auto"/><w:rPr><w:rFonts w:ascii="Helvetica Neue" w:cs="Helvetica Neue" w:eastAsia="Helvetica Neue" w:hAnsi="Helvetica Neue"/><w:color w:val="073763"/></w:rPr></w:pPr><w:r w:rsidDel="00000000" w:rsidR="00000000" w:rsidRPr="00000000"><w:rPr><w:rtl w:val="0"/></w:rPr></w:r></w:p><w:p w:rsidR="00000000" w:rsidDel="00000000" w:rsidP="00000000" w:rsidRDefault="00000000" w:rsidRPr="00000000" w14:paraId="0000002D"><w:pPr><w:tabs><w:tab w:val="left" w:leader="none" w:pos="360"/></w:tabs><w:spacing w:after="0" w:before="0" w:line="240" w:lineRule="auto"/><w:rPr><w:rFonts w:ascii="Helvetica Neue" w:cs="Helvetica Neue" w:eastAsia="Helvetica Neue" w:hAnsi="Helvetica Neue"/><w:color w:val="073763"/></w:rPr></w:pPr><w:r w:rsidDel="00000000" w:rsidR="00000000" w:rsidRPr="00000000"><w:rPr><w:rFonts w:ascii="Helvetica Neue" w:cs="Helvetica Neue" w:eastAsia="Helvetica Neue" w:hAnsi="Helvetica Neue"/><w:color w:val="073763"/><w:rtl w:val="0"/></w:rPr><w:t xml:space="preserve">Strapped tidak bertanggung jawab atas segala hal yang terjadi atas penggunaan pada jalan raya umum dan permasalahan dengan aparat lalu lintas hingga terjadinya pemberian surat tilang,</w:t></w:r></w:p><w:p w:rsidR="00000000" w:rsidDel="00000000" w:rsidP="00000000" w:rsidRDefault="00000000" w:rsidRPr="00000000" w14:paraId="0000002E"><w:pPr><w:tabs><w:tab w:val="left" w:leader="none" w:pos="360"/></w:tabs><w:rPr><w:rFonts w:ascii="Helvetica Neue" w:cs="Helvetica Neue" w:eastAsia="Helvetica Neue" w:hAnsi="Helvetica Neue"/><w:color w:val="073763"/></w:rPr></w:pPr><w:r w:rsidDel="00000000" w:rsidR="00000000" w:rsidRPr="00000000"><w:rPr><w:rtl w:val="0"/></w:rPr></w:r></w:p><w:sectPr><w:headerReference r:id="rId7" w:type="default"/><w:pgSz w:h="16838" w:w="11906" w:orient="portrait"/><w:pgMar w:bottom="720" w:top="720" w:left="720" w:right="720" w:header="720" w:footer="720"/><w:pgNumType w:start="1"/></w:sectPr></w:body></w:document>